circt-1.138.0.dist-info/RECORD
circt-1.138.0.dist-info/WHEEL
circt-1.138.0.dist-info/top_level.txt
circt-1.138.0.dist-info/METADATA
circt/__init__.py
circt/rewrite.py
circt/support.py
circt/ir.py
circt/passmanager.py
circt/extras/types.py
circt/extras/meta.py
circt/_mlir_libs/__init__.py
circt/_mlir_libs/_circt.cpython-310-x86_64-linux-gnu.so
circt/_mlir_libs/_mlirDialectsSMT.cpython-310-x86_64-linux-gnu.so
circt/_mlir_libs/_mlir.cpython-310-x86_64-linux-gnu.so
circt/_mlir_libs/libCIRCTBindingsPythonCAPI.so
circt/_mlir_libs/_mlir/py.typed
circt/dialects/verif.py
circt/dialects/scf.py
circt/dialects/emit.py
circt/dialects/rtgtest.py
circt/dialects/esi.py
circt/dialects/_rtg_ops_gen.py
circt/dialects/_hwarith_ops_gen.py
circt/dialects/fsm.py
circt/dialects/_arc_ops_gen.py
circt/dialects/sv.py
circt/dialects/arc.py
circt/dialects/_synth_ops_gen.py
circt/dialects/_pipeline_ops_gen.py
circt/dialects/index.py
circt/dialects/comb.py
circt/dialects/_fsm_ops_gen.py
circt/dialects/_seq_ops_gen.py
circt/dialects/_index_ops_gen.py
circt/dialects/_index_enum_gen.py
circt/dialects/ltl.py
circt/dialects/_ltl_ops_gen.py
circt/dialects/_esi_ops_gen.py
circt/dialects/_arith_enum_gen.py
circt/dialects/_scf_ops_gen.py
circt/dialects/_verif_ops_gen.py
circt/dialects/_msft_ops_gen.py
circt/dialects/_smt_enum_gen.py
circt/dialects/_dbg_ops_gen.py
circt/dialects/arith.py
circt/dialects/_arith_ops_gen.py
circt/dialects/_comb_ops_gen.py
circt/dialects/_handshake_ops_gen.py
circt/dialects/handshake.py
circt/dialects/smt.py
circt/dialects/pipeline.py
circt/dialects/_smt_ops_gen.py
circt/dialects/om.py
circt/dialects/debug.py
circt/dialects/_hw_ops_gen.py
circt/dialects/synth.py
circt/dialects/_emit_ops_gen.py
circt/dialects/_sv_ops_gen.py
circt/dialects/hw.py
circt/dialects/seq.py
circt/dialects/msft.py
circt/dialects/_om_ops_gen.py
circt/dialects/hwarith.py
circt/dialects/rtg.py
circt/dialects/_rtgtest_ops_gen.py
circt/dialects/_ods_common.py
