Metadata-Version: 2.4
Name: circt
Version: 1.138.0
Summary: CIRCT Python Bindings
Author: Mike Urbach
Author-email: mikeurbach@gmail.com
Dynamic: author
Dynamic: author-email
Dynamic: summary
